{"text_data": {"728128307": "What is my favorite food?", "637541132": "What is my favorite food?", "1985516345": "My favorite food is pizzza.", "1952849039": "My favorite food is pizza.", "1253683100": "My favorite food is pizza.", "1576432149": "My favorite food is pizza.", "468110192": "My favorite food is pizza.", "1970963748": "my favorite food is pizza", "530776958": "My favorite food is pizza", "2126011116": "I like to code.", "1598569117": "I like to BBQ meats."}, "metadata": {"728128307": {"source": "user_message", "type": "chat", "user_id": "test_user", "created_at": "2025-05-02T01:25:09.839709", "importance": 1}, "637541132": {"source": "user_message", "type": "chat", "user_id": "test_user", "created_at": "2025-05-02T01:27:23.621388", "importance": 1}, "1985516345": {"source": "user_message", "type": "chat", "user_id": "streamlit_user_1746153662", "created_at": "2025-05-02T02:41:36.954916", "importance": 1}, "1952849039": {"source": "user_message", "type": "chat", "user_id": "streamlit_user_1746154135", "created_at": "2025-05-02T02:49:54.652013", "importance": 1}, "1253683100": {"source": "user_message", "type": "chat", "user_id": "streamlit_user_1746154135", "created_at": "2025-05-02T02:56:07.516331", "importance": 1}, "1576432149": {"source": "user_message", "type": "chat", "user_id": "streamlit_user_1746155832", "created_at": "2025-05-02T03:17:21.791518", "importance": 1}, "468110192": {"source": "user_message", "type": "chat", "user_id": "streamlit_user_1746157339", "created_at": "2025-05-02T03:42:39.999714", "importance": 1}, "1970963748": {"source": "user_message", "type": "chat", "user_id": "streamlit_user_1746158245", "created_at": "2025-05-02T03:57:42.417488", "importance": 1}, "530776958": {"source": "user_message", "type": "chat", "user_id": "test_user", "created_at": "2025-05-02T04:01:42.841782", "importance": 1}, "2126011116": {"source": "user_message", "type": "chat", "user_id": "streamlit_user_1746158245", "created_at": "2025-05-02T04:10:59.677933", "importance": 1}, "1598569117": {"source": "user_message", "type": "chat", "user_id": "streamlit_user_1746159574", "created_at": "2025-05-02T04:19:46.724287", "importance": 1}}}